{
"meta":{"test_sets":[],"test_metrics":[],"learn_metrics":[{"best_value":"Min","name":"RMSE"}],"launch_mode":"Train","parameters":"","iteration_count":934,"learn_sets":["learn"],"name":"experiment"},
"iterations":[
{"learn":[3.075927309],"iteration":0,"passed_time":0.178997152,"remaining_time":167.0043428},
{"learn":[2.98112042],"iteration":1,"passed_time":0.2036408333,"remaining_time":94.89662831},
{"learn":[2.893350377],"iteration":2,"passed_time":0.2266167659,"remaining_time":70.32673634},
{"learn":[2.812765296],"iteration":3,"passed_time":0.2506336142,"remaining_time":58.27231529},
{"learn":[2.737308006],"iteration":4,"passed_time":0.2787048907,"remaining_time":51.7833687},
{"learn":[2.667700769],"iteration":5,"passed_time":0.3030021236,"remaining_time":46.86432845},
{"learn":[2.602363884],"iteration":6,"passed_time":0.3260771111,"remaining_time":43.181926},
{"learn":[2.543765144],"iteration":7,"passed_time":0.3533191192,"remaining_time":40.89668804},
{"learn":[2.489541309],"iteration":8,"passed_time":0.3776571787,"remaining_time":38.81476558},
{"learn":[2.440125906],"iteration":9,"passed_time":0.4023122097,"remaining_time":37.17364818},
{"learn":[2.393614316],"iteration":10,"passed_time":0.4256112893,"remaining_time":35.71265636},
{"learn":[2.35079811],"iteration":11,"passed_time":0.4492378012,"remaining_time":34.51643773},
{"learn":[2.311385845],"iteration":12,"passed_time":0.4724043038,"remaining_time":33.46802798},
{"learn":[2.276110422],"iteration":13,"passed_time":0.4935247111,"remaining_time":32.43162387},
{"learn":[2.242811651],"iteration":14,"passed_time":0.515612342,"remaining_time":31.58984949},
{"learn":[2.211908469],"iteration":15,"passed_time":0.5364910895,"remaining_time":30.78117626},
{"learn":[2.184328876],"iteration":16,"passed_time":0.5603683556,"remaining_time":30.22692836},
{"learn":[2.157954987],"iteration":17,"passed_time":0.5850900426,"remaining_time":29.77458217},
{"learn":[2.135018063],"iteration":18,"passed_time":0.6067760271,"remaining_time":29.22105604},
{"learn":[2.113323166],"iteration":19,"passed_time":0.6281128825,"remaining_time":28.70475873},
{"learn":[2.093333769],"iteration":20,"passed_time":0.6492558419,"remaining_time":28.22717065},
{"learn":[2.075578339],"iteration":21,"passed_time":0.671929819,"remaining_time":27.85454522},
{"learn":[2.058884098],"iteration":22,"passed_time":0.6942486823,"remaining_time":27.49828477},
{"learn":[2.044897917],"iteration":23,"passed_time":0.7206472807,"remaining_time":27.32454273},
{"learn":[2.030230451],"iteration":24,"passed_time":0.7408027559,"remaining_time":26.93558821},
{"learn":[2.016699922],"iteration":25,"passed_time":0.7641270836,"remaining_time":26.68566892},
{"learn":[2.00359118],"iteration":26,"passed_time":0.7855122732,"remaining_time":26.38739377},
{"learn":[1.992462017],"iteration":27,"passed_time":0.8069264634,"remaining_time":26.10983485},
{"learn":[1.98256816],"iteration":28,"passed_time":0.8311973499,"remaining_time":25.93908971},
{"learn":[1.973410431],"iteration":29,"passed_time":0.8540555479,"remaining_time":25.73554051},
{"learn":[1.965257392],"iteration":30,"passed_time":0.8846488874,"remaining_time":25.76896598},
{"learn":[1.956750687],"iteration":31,"passed_time":0.9152358411,"remaining_time":25.79821027},
{"learn":[1.948787566],"iteration":32,"passed_time":0.9373238416,"remaining_time":25.59178125},
{"learn":[1.941446214],"iteration":33,"passed_time":0.9569844011,"remaining_time":25.33194003},
{"learn":[1.936100833],"iteration":34,"passed_time":0.9808475799,"remaining_time":25.19377069},
{"learn":[1.929751272],"iteration":35,"passed_time":1.006293205,"remaining_time":25.10142495},
{"learn":[1.924247522],"iteration":36,"passed_time":1.028623046,"remaining_time":24.9371587},
{"learn":[1.919840887],"iteration":37,"passed_time":1.050739979,"remaining_time":24.77534267},
{"learn":[1.91548474],"iteration":38,"passed_time":1.074816018,"remaining_time":24.66564965},
{"learn":[1.911046918],"iteration":39,"passed_time":1.10614623,"remaining_time":24.72236825},
{"learn":[1.906388209],"iteration":40,"passed_time":1.130437308,"remaining_time":24.621476},
{"learn":[1.902617369],"iteration":41,"passed_time":1.154633589,"remaining_time":24.52221812},
{"learn":[1.899469237],"iteration":42,"passed_time":1.180015078,"remaining_time":24.45101011},
{"learn":[1.896611259],"iteration":43,"passed_time":1.20234382,"remaining_time":24.32013636},
{"learn":[1.893229998],"iteration":44,"passed_time":1.223282357,"remaining_time":24.16662257},
{"learn":[1.8902566],"iteration":45,"passed_time":1.244450648,"remaining_time":24.02330817},
{"learn":[1.887503806],"iteration":46,"passed_time":1.267752993,"remaining_time":23.92546607},
{"learn":[1.885043101],"iteration":47,"passed_time":1.290904697,"remaining_time":23.82794921},
{"learn":[1.883151706],"iteration":48,"passed_time":1.313864586,"remaining_time":23.73000324},
{"learn":[1.880607262],"iteration":49,"passed_time":1.336532666,"remaining_time":23.62989753},
{"learn":[1.878656952],"iteration":50,"passed_time":1.357889836,"remaining_time":23.51013186},
{"learn":[1.876633339],"iteration":51,"passed_time":1.378573374,"remaining_time":23.3827253},
{"learn":[1.874591309],"iteration":52,"passed_time":1.403380886,"remaining_time":23.32789737},
{"learn":[1.872915124],"iteration":53,"passed_time":1.426493277,"remaining_time":23.24655711},
{"learn":[1.871343821],"iteration":54,"passed_time":1.450123383,"remaining_time":23.17560824},
{"learn":[1.869750966],"iteration":55,"passed_time":1.47183438,"remaining_time":23.07626045},
{"learn":[1.868248026],"iteration":56,"passed_time":1.491854479,"remaining_time":22.95362067},
{"learn":[1.866731563],"iteration":57,"passed_time":1.512877532,"remaining_time":22.84966755},
{"learn":[1.865635832],"iteration":58,"passed_time":1.538424857,"remaining_time":22.81562288},
{"learn":[1.86430575],"iteration":59,"passed_time":1.563417027,"remaining_time":22.77377469},
{"learn":[1.862951798],"iteration":60,"passed_time":1.581000867,"remaining_time":22.62645504},
{"learn":[1.86165738],"iteration":61,"passed_time":1.599841298,"remaining_time":22.50099374},
{"learn":[1.860499487],"iteration":62,"passed_time":1.622313573,"remaining_time":22.42912892},
{"learn":[1.859416369],"iteration":63,"passed_time":1.643672878,"remaining_time":22.34367819},
{"learn":[1.858242351],"iteration":64,"passed_time":1.662665329,"remaining_time":22.22855647},
{"learn":[1.856991152],"iteration":65,"passed_time":1.686343845,"remaining_time":22.17797662},
{"learn":[1.856130425],"iteration":66,"passed_time":1.704968828,"remaining_time":22.06280558},
{"learn":[1.855293078],"iteration":67,"passed_time":1.728540343,"remaining_time":22.01346966},
{"learn":[1.854318727],"iteration":68,"passed_time":1.750556769,"remaining_time":21.94538559},
{"learn":[1.853420482],"iteration":69,"passed_time":1.772168247,"remaining_time":21.87361951},
{"learn":[1.852495064],"iteration":70,"passed_time":1.792384624,"remaining_time":21.78630888},
{"learn":[1.851387089],"iteration":71,"passed_time":1.811835988,"remaining_time":21.69170308},
{"learn":[1.850692058],"iteration":72,"passed_time":1.834692236,"remaining_time":21.63931527},
{"learn":[1.850001967],"iteration":73,"passed_time":1.853784651,"remaining_time":21.54398378},
{"learn":[1.849150453],"iteration":74,"passed_time":1.873145589,"remaining_time":21.45376081},
{"learn":[1.848435528],"iteration":75,"passed_time":1.892631156,"remaining_time":21.36680963},
{"learn":[1.847899064],"iteration":76,"passed_time":1.910273636,"remaining_time":21.26109749},
{"learn":[1.847241678],"iteration":77,"passed_time":1.927329814,"remaining_time":21.15120924},
{"learn":[1.846422215],"iteration":78,"passed_time":1.949125619,"remaining_time":21.09496714},
{"learn":[1.845840392],"iteration":79,"passed_time":1.971787166,"remaining_time":21.048828},
{"learn":[1.845135632],"iteration":80,"passed_time":1.99215546,"remaining_time":20.97911861},
{"learn":[1.844693076],"iteration":81,"passed_time":2.010707054,"remaining_time":20.89173671},
{"learn":[1.844140776],"iteration":82,"passed_time":2.031073475,"remaining_time":20.82462081},
{"learn":[1.843703184],"iteration":83,"passed_time":2.046177855,"remaining_time":20.70537115},
{"learn":[1.842869063],"iteration":84,"passed_time":2.0646343,"remaining_time":20.62205319},
{"learn":[1.842428765],"iteration":85,"passed_time":2.083490925,"remaining_time":20.54418958},
{"learn":[1.841714456],"iteration":86,"passed_time":2.101389582,"remaining_time":20.45835605},
{"learn":[1.841389341],"iteration":87,"passed_time":2.120103026,"remaining_time":20.38189955},
{"learn":[1.840913492],"iteration":88,"passed_time":2.137151518,"remaining_time":20.29093295},
{"learn":[1.840597975],"iteration":89,"passed_time":2.15520962,"remaining_time":20.21107688},
{"learn":[1.840101731],"iteration":90,"passed_time":2.176262615,"remaining_time":20.1603229},
{"learn":[1.839491838],"iteration":91,"passed_time":2.19844979,"remaining_time":20.12059482},
{"learn":[1.839053485],"iteration":92,"passed_time":2.216399713,"remaining_time":20.04292644},
{"learn":[1.838756583],"iteration":93,"passed_time":2.230350967,"remaining_time":19.93079588},
{"learn":[1.838290526],"iteration":94,"passed_time":2.245973613,"remaining_time":19.83549328},
{"learn":[1.837726979],"iteration":95,"passed_time":2.26453441,"remaining_time":19.76749829},
{"learn":[1.837127868],"iteration":96,"passed_time":2.284514658,"remaining_time":19.71277081},
{"learn":[1.836820475],"iteration":97,"passed_time":2.304967978,"remaining_time":19.66278805},
{"learn":[1.836303447],"iteration":98,"passed_time":2.321895714,"remaining_time":19.58366587},
{"learn":[1.835904852],"iteration":99,"passed_time":2.338494063,"remaining_time":19.50304049},
{"learn":[1.835184489],"iteration":100,"passed_time":2.359627266,"remaining_time":19.46108428},
{"learn":[1.834736082],"iteration":101,"passed_time":2.37613394,"remaining_time":19.38179841},
{"learn":[1.834183747],"iteration":102,"passed_time":2.393652041,"remaining_time":19.31189171},
{"learn":[1.833734119],"iteration":103,"passed_time":2.414929885,"remaining_time":19.27299812},
{"learn":[1.833458515],"iteration":104,"passed_time":2.431656083,"remaining_time":19.19850374},
{"learn":[1.83305385],"iteration":105,"passed_time":2.448458656,"remaining_time":19.12569592},
{"learn":[1.832568756],"iteration":106,"passed_time":2.465388666,"remaining_time":19.05491988},
{"learn":[1.83212618],"iteration":107,"passed_time":2.48441161,"remaining_time":19.00114805},
{"learn":[1.831580081],"iteration":108,"passed_time":2.507256851,"remaining_time":18.97694406},
{"learn":[1.831280919],"iteration":109,"passed_time":2.524038663,"remaining_time":18.90734417},
{"learn":[1.830902041],"iteration":110,"passed_time":2.539509266,"remaining_time":18.82897411},
{"learn":[1.830548489],"iteration":111,"passed_time":2.558034286,"remaining_time":18.77414449},
{"learn":[1.830203677],"iteration":112,"passed_time":2.574770796,"remaining_time":18.70696304},
{"learn":[1.829585485],"iteration":113,"passed_time":2.592237583,"remaining_time":18.64591945},
{"learn":[1.829360811],"iteration":114,"passed_time":2.608078839,"remaining_time":18.57405712},
{"learn":[1.828987731],"iteration":115,"passed_time":2.625604397,"remaining_time":18.51503791},
{"learn":[1.828577398],"iteration":116,"passed_time":2.641989712,"remaining_time":18.44876577},
{"learn":[1.828241995],"iteration":117,"passed_time":2.658602741,"remaining_time":18.38491387},
{"learn":[1.82789169],"iteration":118,"passed_time":2.677662586,"remaining_time":18.33861351},
{"learn":[1.827604805],"iteration":119,"passed_time":2.694455679,"remaining_time":18.27739102},
{"learn":[1.827290807],"iteration":120,"passed_time":2.709231656,"remaining_time":18.20334989},
{"learn":[1.826920599],"iteration":121,"passed_time":2.724331166,"remaining_time":18.13243366},
{"learn":[1.826533261],"iteration":122,"passed_time":2.741489984,"remaining_time":18.07600306},
{"learn":[1.826217123],"iteration":123,"passed_time":2.756910014,"remaining_time":18.00884767},
{"learn":[1.825869157],"iteration":124,"passed_time":2.770768445,"remaining_time":17.93241337},
{"learn":[1.825535139],"iteration":125,"passed_time":2.787289326,"remaining_time":17.87404584},
{"learn":[1.825194531],"iteration":126,"passed_time":2.802678267,"remaining_time":17.80914458},
{"learn":[1.824847801],"iteration":127,"passed_time":2.816784745,"remaining_time":17.73694144},
{"learn":[1.824390932],"iteration":128,"passed_time":2.833255314,"remaining_time":17.68039169},
{"learn":[1.824200118],"iteration":129,"passed_time":2.852333751,"remaining_time":17.6405872},
{"learn":[1.823853142],"iteration":130,"passed_time":2.868739177,"remaining_time":17.58471419},
{"learn":[1.823516952],"iteration":131,"passed_time":2.883171068,"remaining_time":17.51744846},
{"learn":[1.82325844],"iteration":132,"passed_time":2.897638745,"remaining_time":17.45119275},
{"learn":[1.822909816],"iteration":133,"passed_time":2.916426178,"remaining_time":17.41149957},
{"learn":[1.822547505],"iteration":134,"passed_time":2.938886528,"remaining_time":17.39385434},
{"learn":[1.822383948],"iteration":135,"passed_time":2.956471661,"remaining_time":17.34753225},
{"learn":[1.82226489],"iteration":136,"passed_time":2.970812411,"remaining_time":17.28275541},
{"learn":[1.822080564],"iteration":137,"passed_time":2.986198653,"remaining_time":17.22474006},
{"learn":[1.82195649],"iteration":138,"passed_time":3.000750898,"remaining_time":17.16256809},
{"learn":[1.821444229],"iteration":139,"passed_time":3.018405853,"remaining_time":17.11867319},
{"learn":[1.82127338],"iteration":140,"passed_time":3.035459299,"remaining_time":17.07176755},
{"learn":[1.820904601],"iteration":141,"passed_time":3.055025409,"remaining_time":17.03929665},
{"learn":[1.820399047],"iteration":142,"passed_time":3.076705381,"remaining_time":17.018699},
{"learn":[1.820289177],"iteration":143,"passed_time":3.095394848,"remaining_time":16.98168007},
{"learn":[1.820079051],"iteration":144,"passed_time":3.109422463,"remaining_time":16.91954706},
{"learn":[1.819808563],"iteration":145,"passed_time":3.125077601,"remaining_time":16.86685719},
{"learn":[1.819721781],"iteration":146,"passed_time":3.139847705,"remaining_time":16.80993295},
{"learn":[1.819606532],"iteration":147,"passed_time":3.157148563,"remaining_time":16.76701872},
{"learn":[1.819344514],"iteration":148,"passed_time":3.172005455,"remaining_time":16.71157237},
{"learn":[1.81896023],"iteration":149,"passed_time":3.18810209,"remaining_time":16.66314692},
{"learn":[1.818511792],"iteration":150,"passed_time":3.207580629,"remaining_time":16.63268631},
{"learn":[1.8182311],"iteration":151,"passed_time":3.22480827,"remaining_time":16.59078991},
{"learn":[1.818166159],"iteration":152,"passed_time":3.239596898,"remaining_time":16.53676587},
{"learn":[1.817954861],"iteration":153,"passed_time":3.255496227,"remaining_time":16.48887699},
{"learn":[1.817748057],"iteration":154,"passed_time":3.272130685,"remaining_time":16.44509551},
{"learn":[1.817420408],"iteration":155,"passed_time":3.288922735,"remaining_time":16.402448},
{"learn":[1.817118149],"iteration":156,"passed_time":3.306288931,"remaining_time":16.36297133},
{"learn":[1.817024796],"iteration":157,"passed_time":3.320595127,"remaining_time":16.30874569},
{"learn":[1.816547248],"iteration":158,"passed_time":3.337223716,"remaining_time":16.26634201},
{"learn":[1.81603395],"iteration":159,"passed_time":3.357584314,"remaining_time":16.24231412},
{"learn":[1.815709512],"iteration":160,"passed_time":3.381001064,"remaining_time":16.23300511},
{"learn":[1.815459362],"iteration":161,"passed_time":3.39704817,"remaining_time":16.18840239},
{"learn":[1.81507756],"iteration":162,"passed_time":3.415536996,"remaining_time":16.15569954},
{"learn":[1.814892471],"iteration":163,"passed_time":3.437091603,"remaining_time":16.13756423},
{"learn":[1.814469807],"iteration":164,"passed_time":3.458398759,"remaining_time":16.11823422},
{"learn":[1.814261291],"iteration":165,"passed_time":3.475602028,"remaining_time":16.07989372},
{"learn":[1.813927227],"iteration":166,"passed_time":3.494495153,"remaining_time":16.04956756},
{"learn":[1.813667177],"iteration":167,"passed_time":3.517791009,"remaining_time":16.03945186},
{"learn":[1.813362346],"iteration":168,"passed_time":3.53628572,"remaining_time":16.00744719},
{"learn":[1.813120372],"iteration":169,"passed_time":3.555281077,"remaining_time":15.97785143},
{"learn":[1.812864309],"iteration":170,"passed_time":3.579809076,"remaining_time":15.97306623},
{"learn":[1.81270911],"iteration":171,"passed_time":3.600850245,"remaining_time":15.95260399},
{"learn":[1.812474046],"iteration":172,"passed_time":3.619497232,"remaining_time":15.92160343},
{"learn":[1.811980361],"iteration":173,"passed_time":3.642851261,"remaining_time":15.91130436},
{"learn":[1.811780575],"iteration":174,"passed_time":3.667773098,"remaining_time":15.90765589},
{"learn":[1.811635221],"iteration":175,"passed_time":3.68411944,"remaining_time":15.86683259},
{"learn":[1.811238932],"iteration":176,"passed_time":3.703077272,"remaining_time":15.83745478},
{"learn":[1.810838687],"iteration":177,"passed_time":3.721434526,"remaining_time":15.80564327},
{"learn":[1.810733871],"iteration":178,"passed_time":3.735205244,"remaining_time":15.75463664},
{"learn":[1.810470082],"iteration":179,"passed_time":3.750545038,"remaining_time":15.71061644},
{"learn":[1.810274174],"iteration":180,"passed_time":3.764024532,"remaining_time":15.65917388},
{"learn":[1.810017641],"iteration":181,"passed_time":3.779859614,"remaining_time":15.61788148},
{"learn":[1.809455688],"iteration":182,"passed_time":3.800229177,"remaining_time":15.59547602},
{"learn":[1.809064288],"iteration":183,"passed_time":3.818414458,"remaining_time":15.56418937},
{"learn":[1.808869346],"iteration":184,"passed_time":3.835011442,"remaining_time":15.52661389},
{"learn":[1.808493711],"iteration":185,"passed_time":3.853773211,"remaining_time":15.49796969},
{"learn":[1.808233529],"iteration":186,"passed_time":3.872532387,"remaining_time":15.46942082},
{"learn":[1.807963704],"iteration":187,"passed_time":3.891972252,"remaining_time":15.44367713},
{"learn":[1.807628567],"iteration":188,"passed_time":3.915016138,"remaining_time":15.43220647},
{"learn":[1.807214103],"iteration":189,"passed_time":3.933891315,"remaining_time":15.4042902},
{"learn":[1.807067512],"iteration":190,"passed_time":3.950074564,"remaining_time":15.36599686},
{"learn":[1.806629459],"iteration":191,"passed_time":3.966950748,"remaining_time":15.33061174},
{"learn":[1.80622469],"iteration":192,"passed_time":3.985403732,"remaining_time":15.30147236},
{"learn":[1.805734476],"iteration":193,"passed_time":4.005122524,"remaining_time":15.27727148},
{"learn":[1.805448033],"iteration":194,"passed_time":4.02168422,"remaining_time":15.24115199},
{"learn":[1.804851368],"iteration":195,"passed_time":4.038321626,"remaining_time":15.20551714},
{"learn":[1.804413093],"iteration":196,"passed_time":4.055440057,"remaining_time":15.17187473},
{"learn":[1.804030274],"iteration":197,"passed_time":4.078444192,"remaining_time":15.1602774},
{"learn":[1.80393414],"iteration":198,"passed_time":4.089953421,"remaining_time":15.10610937},
{"learn":[1.803728763],"iteration":199,"passed_time":4.106617535,"remaining_time":15.07128635},
{"learn":[1.802997315],"iteration":200,"passed_time":4.12645384,"remaining_time":15.04821226},
{"learn":[1.802558899],"iteration":201,"passed_time":4.146005212,"remaining_time":15.0241377},
{"learn":[1.802259694],"iteration":202,"passed_time":4.162168109,"remaining_time":14.98790585},
{"learn":[1.801766865],"iteration":203,"passed_time":4.18325134,"remaining_time":14.96947783},
{"learn":[1.801505834],"iteration":204,"passed_time":4.199773092,"remaining_time":14.93480285},
{"learn":[1.801207444],"iteration":205,"passed_time":4.218754545,"remaining_time":14.90899665},
{"learn":[1.800920869],"iteration":206,"passed_time":4.235781167,"remaining_time":14.87639086},
{"learn":[1.800499754],"iteration":207,"passed_time":4.252246691,"remaining_time":14.84197643},
{"learn":[1.800040887],"iteration":208,"passed_time":4.268521434,"remaining_time":14.80707196},
{"learn":[1.799563846],"iteration":209,"passed_time":4.327313966,"remaining_time":14.91893006},
{"learn":[1.799240682],"iteration":210,"passed_time":4.354183785,"remaining_time":14.91978614},
{"learn":[1.798649997],"iteration":211,"passed_time":4.375923183,"remaining_time":14.9029082},
{"learn":[1.798268304],"iteration":212,"passed_time":4.394011311,"remaining_time":14.87362514},
{"learn":[1.797663728],"iteration":213,"passed_time":4.413460013,"remaining_time":14.84902434},
{"learn":[1.797112503],"iteration":214,"passed_time":4.432603875,"remaining_time":14.82345203},
{"learn":[1.796761107],"iteration":215,"passed_time":4.450051091,"remaining_time":14.79229946},
{"learn":[1.796376059],"iteration":216,"passed_time":4.466791975,"remaining_time":14.75893938},
{"learn":[1.796135344],"iteration":217,"passed_time":4.483184206,"remaining_time":14.72458666},
{"learn":[1.79559037],"iteration":218,"passed_time":4.501550061,"remaining_time":14.69684152},
{"learn":[1.79475048],"iteration":219,"passed_time":4.520493303,"remaining_time":14.67105554},
{"learn":[1.794416746],"iteration":220,"passed_time":4.537879353,"remaining_time":14.6403076},
{"learn":[1.794069668],"iteration":221,"passed_time":4.555767198,"remaining_time":14.61128939},
{"learn":[1.793539785],"iteration":222,"passed_time":4.57358483,"remaining_time":14.58214715},
{"learn":[1.793057935],"iteration":223,"passed_time":4.586713117,"remaining_time":14.53824247},
{"learn":[1.792453337],"iteration":224,"passed_time":4.603276552,"remaining_time":14.50543589},
{"learn":[1.791766148],"iteration":225,"passed_time":4.622414033,"remaining_time":14.48083688},
{"learn":[1.791247763],"iteration":226,"passed_time":4.641784818,"remaining_time":14.45701263},
{"learn":[1.791029634],"iteration":227,"passed_time":4.656916868,"remaining_time":14.42010223},
{"learn":[1.790895098],"iteration":228,"passed_time":4.671270448,"remaining_time":14.38098544},
{"learn":[1.790511015],"iteration":229,"passed_time":4.692802161,"remaining_time":14.36405531},
{"learn":[1.790059773],"iteration":230,"passed_time":4.724144681,"remaining_time":14.37694247},
{"learn":[1.789878302],"iteration":231,"passed_time":4.746983776,"remaining_time":14.36371815},
{"learn":[1.78953246],"iteration":232,"passed_time":4.767285709,"remaining_time":14.34277803},
{"learn":[1.789139197],"iteration":233,"passed_time":4.78769195,"remaining_time":14.3221554},
{"learn":[1.7888848],"iteration":234,"passed_time":4.809351509,"remaining_time":14.30526257},
{"learn":[1.788129743],"iteration":235,"passed_time":4.834648937,"remaining_time":14.29908881},
{"learn":[1.78752714],"iteration":236,"passed_time":4.858181,"remaining_time":14.28756184},
{"learn":[1.787066488],"iteration":237,"passed_time":4.877784143,"remaining_time":14.26444439},
{"learn":[1.786671042],"iteration":238,"passed_time":4.900406782,"remaining_time":14.25013688},
{"learn":[1.785699918],"iteration":239,"passed_time":4.92792335,"remaining_time":14.24991169},
{"learn":[1.784651058],"iteration":240,"passed_time":4.955351429,"remaining_time":14.24920556},
{"learn":[1.784386699],"iteration":241,"passed_time":4.979633739,"remaining_time":14.23928325},
{"learn":[1.783806884],"iteration":242,"passed_time":5.008363074,"remaining_time":14.24188841},
{"learn":[1.783269912],"iteration":243,"passed_time":5.028644294,"remaining_time":14.22034657},
{"learn":[1.782700222],"iteration":244,"passed_time":5.051201295,"remaining_time":14.20521507},
{"learn":[1.782281997],"iteration":245,"passed_time":5.072432787,"remaining_time":14.18631609},
{"learn":[1.781461387],"iteration":246,"passed_time":5.093117561,"remaining_time":14.16587759},
{"learn":[1.78132276],"iteration":247,"passed_time":5.108168938,"remaining_time":14.1298544},
{"learn":[1.780765532],"iteration":248,"passed_time":5.126019849,"remaining_time":14.10170119},
{"learn":[1.780288955],"iteration":249,"passed_time":5.144185323,"remaining_time":14.07449104},
{"learn":[1.779574179],"iteration":250,"passed_time":5.164138847,"remaining_time":14.05221846},
{"learn":[1.779087262],"iteration":251,"passed_time":5.181310023,"remaining_time":14.02243427},
{"learn":[1.778727913],"iteration":252,"passed_time":5.199949126,"remaining_time":13.99670101},
{"learn":[1.778212856],"iteration":253,"passed_time":5.219062708,"remaining_time":13.97229386},
{"learn":[1.7776777],"iteration":254,"passed_time":5.242636818,"remaining_time":13.95980549},
{"learn":[1.777582367],"iteration":255,"passed_time":5.259057667,"remaining_time":13.92828554},
{"learn":[1.777105202],"iteration":256,"passed_time":5.279872613,"remaining_time":13.9084582},
{"learn":[1.776524583],"iteration":257,"passed_time":5.29536427,"remaining_time":13.87467538},
{"learn":[1.776123718],"iteration":258,"passed_time":5.312138711,"remaining_time":13.84437695},
{"learn":[1.775678735],"iteration":259,"passed_time":5.33376407,"remaining_time":13.82675763},
{"learn":[1.775453029],"iteration":260,"passed_time":5.350901607,"remaining_time":13.79753556},
{"learn":[1.774902307],"iteration":261,"passed_time":5.371139062,"remaining_time":13.77635668},
{"learn":[1.774423341],"iteration":262,"passed_time":5.385039104,"remaining_time":13.73901612},
{"learn":[1.773989182],"iteration":263,"passed_time":5.398470615,"remaining_time":13.70066406},
{"learn":[1.773431982],"iteration":264,"passed_time":5.416350479,"remaining_time":13.67373008},
{"learn":[1.773151953],"iteration":265,"passed_time":5.434186618,"remaining_time":13.64675436},
{"learn":[1.772716152],"iteration":266,"passed_time":5.449526583,"remaining_time":13.61361135},
{"learn":[1.772121174],"iteration":267,"passed_time":5.466286558,"remaining_time":13.58413003},
{"learn":[1.771593084],"iteration":268,"passed_time":5.489417484,"remaining_time":13.57049304},
{"learn":[1.771288964],"iteration":269,"passed_time":5.505627717,"remaining_time":13.53976594},
{"learn":[1.771052882],"iteration":270,"passed_time":5.52463513,"remaining_time":13.51598927},
{"learn":[1.770678165],"iteration":271,"passed_time":5.544182167,"remaining_time":13.49356101},
{"learn":[1.770174783],"iteration":272,"passed_time":5.565166937,"remaining_time":13.47463497},
{"learn":[1.769760899],"iteration":273,"passed_time":5.579996449,"remaining_time":13.44086736},
{"learn":[1.769220313],"iteration":274,"passed_time":5.597959827,"remaining_time":13.41474737},
{"learn":[1.768707756],"iteration":275,"passed_time":5.618519972,"remaining_time":13.39487732},
{"learn":[1.768612774],"iteration":276,"passed_time":5.633051835,"remaining_time":13.36070417},
{"learn":[1.76813001],"iteration":277,"passed_time":5.646272431,"remaining_time":13.32357811},
{"learn":[1.767974481],"iteration":278,"passed_time":5.663744018,"remaining_time":13.29660334},
{"learn":[1.767454467],"iteration":279,"passed_time":5.687010542,"remaining_time":13.28323177},
{"learn":[1.766834648],"iteration":280,"passed_time":5.709816646,"remaining_time":13.26871982},
{"learn":[1.766299085],"iteration":281,"passed_time":5.731300675,"remaining_time":13.25109234},
{"learn":[1.766068935],"iteration":282,"passed_time":5.752485302,"remaining_time":13.23274888},
{"learn":[1.765774882],"iteration":283,"passed_time":5.773096903,"remaining_time":13.2130739},
{"learn":[1.765096347],"iteration":284,"passed_time":5.798191259,"remaining_time":13.20360045},
{"learn":[1.764881087],"iteration":285,"passed_time":5.823846157,"remaining_time":13.1952878},
{"learn":[1.764122417],"iteration":286,"passed_time":5.849974249,"remaining_time":13.18792104},
{"learn":[1.763261791],"iteration":287,"passed_time":5.8724437,"remaining_time":13.17221747},
{"learn":[1.763101381],"iteration":288,"passed_time":5.893867166,"remaining_time":13.1541326},
{"learn":[1.762749916],"iteration":289,"passed_time":5.912560168,"remaining_time":13.1299612},
{"learn":[1.762227183],"iteration":290,"passed_time":5.929022009,"remaining_time":13.10089743},
{"learn":[1.762122535],"iteration":291,"passed_time":5.94884748,"remaining_time":13.07931535},
{"learn":[1.761509228],"iteration":292,"passed_time":5.968289513,"remaining_time":13.05690641},
{"learn":[1.761318454],"iteration":293,"passed_time":5.985213617,"remaining_time":13.02903644},
{"learn":[1.760983754],"iteration":294,"passed_time":6.000256681,"remaining_time":12.99716617},
{"learn":[1.760832602],"iteration":295,"passed_time":6.017268629,"remaining_time":12.96965333},
{"learn":[1.760610672],"iteration":296,"passed_time":6.037484828,"remaining_time":12.94908362},
{"learn":[1.760273237],"iteration":297,"passed_time":6.05456032,"remaining_time":12.9218133},
{"learn":[1.75956504],"iteration":298,"passed_time":6.079877276,"remaining_time":12.91211395},
{"learn":[1.758870499],"iteration":299,"passed_time":6.102298455,"remaining_time":12.89619074},
{"learn":[1.758489379],"iteration":300,"passed_time":6.119649728,"remaining_time":12.86956238},
{"learn":[1.758152339],"iteration":301,"passed_time":6.134289385,"remaining_time":12.83732083},
{"learn":[1.757678691],"iteration":302,"passed_time":6.151723585,"remaining_time":12.81101512},
{"learn":[1.757396601],"iteration":303,"passed_time":6.170050054,"remaining_time":12.78661689},
{"learn":[1.757102838],"iteration":304,"passed_time":6.190034851,"remaining_time":12.76567843},
{"learn":[1.756913503],"iteration":305,"passed_time":6.208861164,"remaining_time":12.74236866},
{"learn":[1.756212841],"iteration":306,"passed_time":6.231080478,"remaining_time":12.72601778},
{"learn":[1.756030816],"iteration":307,"passed_time":6.251268984,"remaining_time":12.70550125},
{"learn":[1.755298902],"iteration":308,"passed_time":6.271201549,"remaining_time":12.68446915},
{"learn":[1.754833843],"iteration":309,"passed_time":6.291405079,"remaining_time":12.66398958},
{"learn":[1.754274433],"iteration":310,"passed_time":6.314588855,"remaining_time":12.64948185},
{"learn":[1.753315039],"iteration":311,"passed_time":6.33895859,"remaining_time":12.63728283},
{"learn":[1.753203441],"iteration":312,"passed_time":6.361885698,"remaining_time":12.62214383},
{"learn":[1.752455688],"iteration":313,"passed_time":6.380428185,"remaining_time":12.59829769},
{"learn":[1.752072005],"iteration":314,"passed_time":6.393945362,"remaining_time":12.56461009},
{"learn":[1.751411001],"iteration":315,"passed_time":6.412660239,"remaining_time":12.54121528},
{"learn":[1.750757077],"iteration":316,"passed_time":6.432480275,"remaining_time":12.52000104},
{"learn":[1.749966873],"iteration":317,"passed_time":6.454903294,"remaining_time":12.50383783},
{"learn":[1.749638279],"iteration":318,"passed_time":6.472856819,"remaining_time":12.47901863},
{"learn":[1.749085641],"iteration":319,"passed_time":6.492463907,"remaining_time":12.45741512},
{"learn":[1.748829108],"iteration":320,"passed_time":6.511009411,"remaining_time":12.43379679},
{"learn":[1.74833409],"iteration":321,"passed_time":6.533276868,"remaining_time":12.41728398},
{"learn":[1.748229274],"iteration":322,"passed_time":6.552381868,"remaining_time":12.39475332},
{"learn":[1.748083888],"iteration":323,"passed_time":6.56990417,"remaining_time":12.36926402},
{"learn":[1.747250197],"iteration":324,"passed_time":6.590982665,"remaining_time":12.35048752},
{"learn":[1.746962169],"iteration":325,"passed_time":6.606077443,"remaining_time":12.32053707},
{"learn":[1.746392625],"iteration":326,"passed_time":6.627947659,"remaining_time":12.30325452},
{"learn":[1.745607978],"iteration":327,"passed_time":6.648387276,"remaining_time":12.28330088},
{"learn":[1.745288312],"iteration":328,"passed_time":6.665861739,"remaining_time":12.25789165},
{"learn":[1.74469436],"iteration":329,"passed_time":6.684853214,"remaining_time":12.23530709},
{"learn":[1.744391199],"iteration":330,"passed_time":6.700688245,"remaining_time":12.20699399},
{"learn":[1.744110532],"iteration":331,"passed_time":6.719382962,"remaining_time":12.1839414},
{"learn":[1.743910245],"iteration":332,"passed_time":6.739438838,"remaining_time":12.1633716},
{"learn":[1.74358876],"iteration":333,"passed_time":6.753254839,"remaining_time":12.13159552},
{"learn":[1.743270936],"iteration":334,"passed_time":6.76857619,"remaining_time":12.10261832},
{"learn":[1.742503501],"iteration":335,"passed_time":6.787226237,"remaining_time":12.0796467},
{"learn":[1.741847884],"iteration":336,"passed_time":6.806237813,"remaining_time":12.05734117},
{"learn":[1.741424504],"iteration":337,"passed_time":6.827643853,"remaining_time":12.03927733},
{"learn":[1.741079362],"iteration":338,"passed_time":6.846230762,"remaining_time":12.01624573},
{"learn":[1.740633183],"iteration":339,"passed_time":6.868644697,"remaining_time":11.99992632},
{"learn":[1.74021336],"iteration":340,"passed_time":6.891557421,"remaining_time":11.98443856},
{"learn":[1.739874434],"iteration":341,"passed_time":6.912221749,"remaining_time":11.96501543},
{"learn":[1.739381046],"iteration":342,"passed_time":6.933603574,"remaining_time":11.94682132},
{"learn":[1.73886662],"iteration":343,"passed_time":6.954065291,"remaining_time":11.92703059},
{"learn":[1.738783257],"iteration":344,"passed_time":6.977109289,"remaining_time":11.91164455},
{"learn":[1.738244459],"iteration":345,"passed_time":6.996016694,"remaining_time":11.88918444},
{"learn":[1.737906093],"iteration":346,"passed_time":7.017504599,"remaining_time":11.87111009},
{"learn":[1.737594385],"iteration":347,"passed_time":7.034919264,"remaining_time":11.84615715},
{"learn":[1.73714279],"iteration":348,"passed_time":7.05452881,"remaining_time":11.82492652},
{"learn":[1.736956778],"iteration":349,"passed_time":7.076275937,"remaining_time":11.80727185},
{"learn":[1.736488587],"iteration":350,"passed_time":7.09606476,"remaining_time":11.78634118},
{"learn":[1.736088211],"iteration":351,"passed_time":7.117123083,"remaining_time":11.76751601},
{"learn":[1.735937425],"iteration":352,"passed_time":7.135714083,"remaining_time":11.74461723},
{"learn":[1.735209766],"iteration":353,"passed_time":7.15972462,"remaining_time":11.73062226},
{"learn":[1.734955901],"iteration":354,"passed_time":7.178564399,"remaining_time":11.70813743},
{"learn":[1.734860087],"iteration":355,"passed_time":7.193329147,"remaining_time":11.67905687},
{"learn":[1.734803576],"iteration":356,"passed_time":7.2049337,"remaining_time":11.64494887},
{"learn":[1.734422751],"iteration":357,"passed_time":7.219808551,"remaining_time":11.61622828},
{"learn":[1.734230709],"iteration":358,"passed_time":7.235712614,"remaining_time":11.58923329},
{"learn":[1.733913113],"iteration":359,"passed_time":7.257793075,"remaining_time":11.57214785},
{"learn":[1.733566143],"iteration":360,"passed_time":7.276199356,"remaining_time":11.54920286},
{"learn":[1.733527587],"iteration":361,"passed_time":7.294167454,"remaining_time":11.52559056},
{"learn":[1.732967052],"iteration":362,"passed_time":7.313307754,"remaining_time":11.50385324},
{"learn":[1.732568292],"iteration":363,"passed_time":7.332298999,"remaining_time":11.48189678},
{"learn":[1.732027593],"iteration":364,"passed_time":7.351120789,"remaining_time":11.45969241},
{"learn":[1.731565686],"iteration":365,"passed_time":7.375136324,"remaining_time":11.44556675},
{"learn":[1.731342275],"iteration":366,"passed_time":7.395671073,"remaining_time":11.42600953},
{"learn":[1.731076301],"iteration":367,"passed_time":7.41630313,"remaining_time":11.40659666},
{"learn":[1.730901429],"iteration":368,"passed_time":7.438028914,"remaining_time":11.38885186},
{"learn":[1.730245835],"iteration":369,"passed_time":7.459204929,"remaining_time":11.37024751},
{"learn":[1.72990638],"iteration":370,"passed_time":7.478043462,"remaining_time":11.34808213},
{"learn":[1.729095159],"iteration":371,"passed_time":7.498037731,"remaining_time":11.32768066},
{"learn":[1.728947505],"iteration":372,"passed_time":7.516509624,"remaining_time":11.30499169},
{"learn":[1.728621719],"iteration":373,"passed_time":7.534655743,"remaining_time":11.28183748},
{"learn":[1.728175505],"iteration":374,"passed_time":7.555797548,"remaining_time":11.26317554},
{"learn":[1.727779121],"iteration":375,"passed_time":7.576999997,"remaining_time":11.24459042},
{"learn":[1.727415305],"iteration":376,"passed_time":7.596324035,"remaining_time":11.22321615},
{"learn":[1.727277457],"iteration":377,"passed_time":7.613817328,"remaining_time":11.19915988},
{"learn":[1.726751862],"iteration":378,"passed_time":7.632998685,"remaining_time":11.17761021},
{"learn":[1.726148979],"iteration":379,"passed_time":7.653806335,"remaining_time":11.15844397},
{"learn":[1.725817211],"iteration":380,"passed_time":7.669469289,"remaining_time":11.13180188},
{"learn":[1.725717601],"iteration":381,"passed_time":7.689118404,"remaining_time":11.11097738},
{"learn":[1.72528644],"iteration":382,"passed_time":7.709539345,"remaining_time":11.0912694},
{"learn":[1.724540491],"iteration":383,"passed_time":7.731575791,"remaining_time":11.07387158},
{"learn":[1.724093674],"iteration":384,"passed_time":7.750658611,"remaining_time":11.05223786},
{"learn":[1.723573961],"iteration":385,"passed_time":7.769671097,"remaining_time":11.03051752},
{"learn":[1.723470304],"iteration":386,"passed_time":7.789955562,"remaining_time":11.01060902},
{"learn":[1.72339239],"iteration":387,"passed_time":7.810101512,"remaining_time":10.99050367},
{"learn":[1.723357698],"iteration":388,"passed_time":7.828822614,"remaining_time":10.96840186},
{"learn":[1.72296285],"iteration":389,"passed_time":7.847746146,"remaining_time":10.94659975},
{"learn":[1.722547275],"iteration":390,"passed_time":7.86609789,"remaining_time":10.9240183},
{"learn":[1.72219816],"iteration":391,"passed_time":7.885640364,"remaining_time":10.90310479},
{"learn":[1.722069807],"iteration":392,"passed_time":7.903661281,"remaining_time":10.8801037},
{"learn":[1.721675154],"iteration":393,"passed_time":7.922615543,"remaining_time":10.85840709},
{"learn":[1.721316795],"iteration":394,"passed_time":7.938248356,"remaining_time":10.83219206},
{"learn":[1.720888801],"iteration":395,"passed_time":7.958924981,"remaining_time":10.81288293},
{"learn":[1.720778471],"iteration":396,"passed_time":7.982461701,"remaining_time":10.7974356},
{"learn":[1.720648972],"iteration":397,"passed_time":8.004776692,"remaining_time":10.78030228},
{"learn":[1.720114456],"iteration":398,"passed_time":8.027738229,"remaining_time":10.76400991},
{"learn":[1.719835286],"iteration":399,"passed_time":8.051889422,"remaining_time":10.74927238},
{"learn":[1.719311629],"iteration":400,"passed_time":8.073949494,"remaining_time":10.73170843},
{"learn":[1.719092774],"iteration":401,"passed_time":8.096528706,"remaining_time":10.71480913},
{"learn":[1.718682565],"iteration":402,"passed_time":8.124095963,"remaining_time":10.70445399},
{"learn":[1.718577001],"iteration":403,"passed_time":8.147973037,"remaining_time":10.68917255},
{"learn":[1.718198646],"iteration":404,"passed_time":8.171883322,"remaining_time":10.67389204},
{"learn":[1.717682292],"iteration":405,"passed_time":8.194392798,"remaining_time":10.65674728},
{"learn":[1.71736861],"iteration":406,"passed_time":8.213690301,"remaining_time":10.63541717},
{"learn":[1.716831912],"iteration":407,"passed_time":8.238795375,"remaining_time":10.62158423},
{"learn":[1.716644642],"iteration":408,"passed_time":8.256620282,"remaining_time":10.59835122},
{"learn":[1.716494216],"iteration":409,"passed_time":8.27482413,"remaining_time":10.57562889},
{"learn":[1.715739555],"iteration":410,"passed_time":8.294205467,"remaining_time":10.55442691},
{"learn":[1.715309343],"iteration":411,"passed_time":8.31397036,"remaining_time":10.53371973},
{"learn":[1.714764158],"iteration":412,"passed_time":8.335340417,"remaining_time":10.51504203},
{"learn":[1.714451735],"iteration":413,"passed_time":8.349330347,"remaining_time":10.48708159},
{"learn":[1.71409982],"iteration":414,"passed_time":8.367970797,"remaining_time":10.46500444},
{"learn":[1.713953848],"iteration":415,"passed_time":8.386159597,"remaining_time":10.44238142},
{"learn":[1.713793412],"iteration":416,"passed_time":8.404827001,"remaining_time":10.42037304},
{"learn":[1.713117359],"iteration":417,"passed_time":8.42721708,"remaining_time":10.40297611},
{"learn":[1.712443322],"iteration":418,"passed_time":8.447322492,"remaining_time":10.38274722},
{"learn":[1.711929867],"iteration":419,"passed_time":8.469507468,"remaining_time":10.3650639},
{"learn":[1.711884955],"iteration":420,"passed_time":8.490299652,"remaining_time":10.34566205},
{"learn":[1.71152342],"iteration":421,"passed_time":8.51457869,"remaining_time":10.3304841},
{"learn":[1.711410104],"iteration":422,"passed_time":8.538453373,"remaining_time":10.31477464},
{"learn":[1.711151889],"iteration":423,"passed_time":8.557729611,"remaining_time":10.29349552},
{"learn":[1.710701356],"iteration":424,"passed_time":8.576252407,"remaining_time":10.27132347},
{"learn":[1.71013808],"iteration":425,"passed_time":8.596177266,"remaining_time":10.2508405},
{"learn":[1.70976101],"iteration":426,"passed_time":8.616617876,"remaining_time":10.23097251},
{"learn":[1.709327651],"iteration":427,"passed_time":8.637535939,"remaining_time":10.21166632},
{"learn":[1.708889477],"iteration":428,"passed_time":8.657007597,"remaining_time":10.19064997},
{"learn":[1.708678315],"iteration":429,"passed_time":8.675604487,"remaining_time":10.16861549},
{"learn":[1.708010791],"iteration":430,"passed_time":8.695397506,"remaining_time":10.14799291},
{"learn":[1.707413016],"iteration":431,"passed_time":8.715372753,"remaining_time":10.12758593},
{"learn":[1.706957617],"iteration":432,"passed_time":8.735304695,"remaining_time":10.10713084},
{"learn":[1.7068939],"iteration":433,"passed_time":8.755004925,"remaining_time":10.0864112},
{"learn":[1.706715137],"iteration":434,"passed_time":8.773706853,"remaining_time":10.06455108},
{"learn":[1.706148235],"iteration":435,"passed_time":8.793507326,"remaining_time":10.0439602},
{"learn":[1.705754063],"iteration":436,"passed_time":8.815373028,"remaining_time":10.02572173},
{"learn":[1.705308269],"iteration":437,"passed_time":8.842131041,"remaining_time":10.01300684},
{"learn":[1.705113898],"iteration":438,"passed_time":8.864549968,"remaining_time":9.995335385},
{"learn":[1.704421198],"iteration":439,"passed_time":8.889243341,"remaining_time":9.980195933},
{"learn":[1.704090937],"iteration":440,"passed_time":8.91265537,"remaining_time":9.963580719},
{"learn":[1.703512068],"iteration":441,"passed_time":8.937754321,"remaining_time":9.948812502},
{"learn":[1.702773332],"iteration":442,"passed_time":8.962549747,"remaining_time":9.933661232},
{"learn":[1.701933821],"iteration":443,"passed_time":8.990474445,"remaining_time":9.921919995},
{"learn":[1.701381712],"iteration":444,"passed_time":9.016435976,"remaining_time":9.907948747},
{"learn":[1.701244038],"iteration":445,"passed_time":9.038274557,"remaining_time":9.88941252},
{"learn":[1.700780674],"iteration":446,"passed_time":9.065079645,"remaining_time":9.876272454},
{"learn":[1.700536498],"iteration":447,"passed_time":9.092045453,"remaining_time":9.863245736},
{"learn":[1.700241851],"iteration":448,"passed_time":9.119687869,"remaining_time":9.850887787},
{"learn":[1.700053457],"iteration":449,"passed_time":9.139546465,"remaining_time":9.830089975},
{"learn":[1.699647831],"iteration":450,"passed_time":9.156617955,"remaining_time":9.806311468},
{"learn":[1.699373304],"iteration":451,"passed_time":9.174776404,"remaining_time":9.783721741},
{"learn":[1.698985942],"iteration":452,"passed_time":9.193200834,"remaining_time":9.761433998},
{"learn":[1.69861399],"iteration":453,"passed_time":9.212127495,"remaining_time":9.739694268},
{"learn":[1.698549204],"iteration":454,"passed_time":9.230840081,"remaining_time":9.717741536},
{"learn":[1.698175867],"iteration":455,"passed_time":9.250725276,"remaining_time":9.697032197},
{"learn":[1.697797722],"iteration":456,"passed_time":9.269107331,"remaining_time":9.674757543},
{"learn":[1.697741853],"iteration":457,"passed_time":9.287437979,"remaining_time":9.652446458},
{"learn":[1.697143549],"iteration":458,"passed_time":9.308265381,"remaining_time":9.632736505},
{"learn":[1.696697574],"iteration":459,"passed_time":9.327962087,"remaining_time":9.611856586},
{"learn":[1.696504338],"iteration":460,"passed_time":9.342923653,"remaining_time":9.586123401},
{"learn":[1.696219489],"iteration":461,"passed_time":9.356611329,"remaining_time":9.559135384},
{"learn":[1.695828372],"iteration":462,"passed_time":9.374918782,"remaining_time":9.53690442},
{"learn":[1.695492501],"iteration":463,"passed_time":9.397285988,"remaining_time":9.518802617},
{"learn":[1.69540302],"iteration":464,"passed_time":9.410161987,"remaining_time":9.491109617},
{"learn":[1.695123241],"iteration":465,"passed_time":9.428909822,"remaining_time":9.469377246},
{"learn":[1.694617685],"iteration":466,"passed_time":9.44779915,"remaining_time":9.44779915},
{"learn":[1.694326307],"iteration":467,"passed_time":9.465149611,"remaining_time":9.424700254},
{"learn":[1.693999773],"iteration":468,"passed_time":9.483485078,"remaining_time":9.402602476},
{"learn":[1.69320054],"iteration":469,"passed_time":9.503877571,"remaining_time":9.382551474},
{"learn":[1.692801102],"iteration":470,"passed_time":9.520432837,"remaining_time":9.358726971},
{"learn":[1.692774285],"iteration":471,"passed_time":9.538781627,"remaining_time":9.336688796},
{"learn":[1.692552402],"iteration":472,"passed_time":9.557217777,"remaining_time":9.314751364},
{"learn":[1.692451106],"iteration":473,"passed_time":9.578009517,"remaining_time":9.295114721},
{"learn":[1.691905638],"iteration":474,"passed_time":9.600208682,"remaining_time":9.276833231},
{"learn":[1.691832957],"iteration":475,"passed_time":9.622713564,"remaining_time":9.258829438},
{"learn":[1.691412201],"iteration":476,"passed_time":9.644958003,"remaining_time":9.240557248},
{"learn":[1.691022021],"iteration":477,"passed_time":9.66545845,"remaining_time":9.220604714},
{"learn":[1.690505817],"iteration":478,"passed_time":9.69011934,"remaining_time":9.204601878},
{"learn":[1.690411093],"iteration":479,"passed_time":9.71050528,"remaining_time":9.184519577},
{"learn":[1.690113977],"iteration":480,"passed_time":9.733769222,"remaining_time":9.167146482},
{"learn":[1.689952959],"iteration":481,"passed_time":9.753781105,"remaining_time":9.146699293},
{"learn":[1.689907249],"iteration":482,"passed_time":9.770626224,"remaining_time":9.12329695},
{"learn":[1.689771793],"iteration":483,"passed_time":9.790823071,"remaining_time":9.10303798},
{"learn":[1.689724404],"iteration":484,"passed_time":9.811975829,"remaining_time":9.083664221},
{"learn":[1.689421728],"iteration":485,"passed_time":9.855070028,"remaining_time":9.084508997},
{"learn":[1.689086592],"iteration":486,"passed_time":9.910297531,"remaining_time":9.096310054},
{"learn":[1.689065556],"iteration":487,"passed_time":9.94198367,"remaining_time":9.086321141},
{"learn":[1.688643048],"iteration":488,"passed_time":9.97752545,"remaining_time":9.079752199},
{"learn":[1.688076486],"iteration":489,"passed_time":10.00003583,"remaining_time":9.061256958},
{"learn":[1.687515685],"iteration":490,"passed_time":10.02196925,"remaining_time":9.042224805},
{"learn":[1.687452205],"iteration":491,"passed_time":10.04434089,"remaining_time":9.023574539},
{"learn":[1.687134222],"iteration":492,"passed_time":10.06516877,"remaining_time":9.003528255},
{"learn":[1.686766479],"iteration":493,"passed_time":10.08766981,"remaining_time":8.984969059},
{"learn":[1.686666345],"iteration":494,"passed_time":10.10873445,"remaining_time":8.96512005},
{"learn":[1.686312345],"iteration":495,"passed_time":10.13057245,"remaining_time":8.945949058},
{"learn":[1.686094236],"iteration":496,"passed_time":10.15381189,"remaining_time":8.927999586},
{"learn":[1.685910361],"iteration":497,"passed_time":10.17732161,"remaining_time":8.910265504},
{"learn":[1.685787496],"iteration":498,"passed_time":10.20162761,"remaining_time":8.893202423},
{"learn":[1.685609469],"iteration":499,"passed_time":10.22640928,"remaining_time":8.876523251},
{"learn":[1.685106156],"iteration":500,"passed_time":10.24897458,"remaining_time":8.857896193},
{"learn":[1.684797427],"iteration":501,"passed_time":10.27046893,"remaining_time":8.838331827},
{"learn":[1.684330633],"iteration":502,"passed_time":10.29497491,"remaining_time":8.821340328},
{"learn":[1.6839885],"iteration":503,"passed_time":10.31651398,"remaining_time":8.80178772},
{"learn":[1.683803649],"iteration":504,"passed_time":10.33709975,"remaining_time":8.781417414},
{"learn":[1.683488578],"iteration":505,"passed_time":10.35911443,"remaining_time":8.762254897},
{"learn":[1.683452541],"iteration":506,"passed_time":10.37954735,"remaining_time":8.741748949},
{"learn":[1.682885845],"iteration":507,"passed_time":10.40250289,"remaining_time":8.723358723},
{"learn":[1.682337294],"iteration":508,"passed_time":10.4262258,"remaining_time":8.705591284},
{"learn":[1.681807411],"iteration":509,"passed_time":10.44749874,"remaining_time":8.68576366},
{"learn":[1.681524036],"iteration":510,"passed_time":10.46955291,"remaining_time":8.666577063},
{"learn":[1.681059392],"iteration":511,"passed_time":10.49230279,"remaining_time":8.647952693},
{"learn":[1.68100189],"iteration":512,"passed_time":10.51215214,"remaining_time":8.626931877},
{"learn":[1.680292822],"iteration":513,"passed_time":10.53529401,"remaining_time":8.608606003},
{"learn":[1.679941215],"iteration":514,"passed_time":10.55801474,"remaining_time":8.589918788},
{"learn":[1.679735031],"iteration":515,"passed_time":10.57899996,"remaining_time":8.569810048},
{"learn":[1.679342103],"iteration":516,"passed_time":10.59958479,"remaining_time":8.549374968},
{"learn":[1.679055111],"iteration":517,"passed_time":10.61933631,"remaining_time":8.528270089},
{"learn":[1.678731128],"iteration":518,"passed_time":10.63964957,"remaining_time":8.507619594},
{"learn":[1.678651981],"iteration":519,"passed_time":10.66282825,"remaining_time":8.48925172},
{"learn":[1.678539407],"iteration":520,"passed_time":10.6860145,"remaining_time":8.470871381},
{"learn":[1.678008934],"iteration":521,"passed_time":10.71067105,"remaining_time":8.453633089},
{"learn":[1.677660325],"iteration":522,"passed_time":10.73336095,"remaining_time":8.434820938},
{"learn":[1.677162241],"iteration":523,"passed_time":10.7546198,"remaining_time":8.41487427},
{"learn":[1.676706646],"iteration":524,"passed_time":10.77594571,"remaining_time":8.394974847},
{"learn":[1.676640652],"iteration":525,"passed_time":10.79133119,"remaining_time":8.370462217},
{"learn":[1.67599817],"iteration":526,"passed_time":10.81271683,"remaining_time":8.350618119},
{"learn":[1.675849232],"iteration":527,"passed_time":10.83008101,"remaining_time":8.327675929},
{"learn":[1.675667208],"iteration":528,"passed_time":10.84872968,"remaining_time":8.305738223},
{"learn":[1.675638734],"iteration":529,"passed_time":10.86708059,"remaining_time":8.283585957},
{"learn":[1.675316774],"iteration":530,"passed_time":10.8892046,"remaining_time":8.264311586},
{"learn":[1.67483245],"iteration":531,"passed_time":10.90955549,"remaining_time":8.24368667},
{"learn":[1.674578968],"iteration":532,"passed_time":10.92851067,"remaining_time":8.222012722},
{"learn":[1.674116001],"iteration":533,"passed_time":10.9492078,"remaining_time":8.201653783},
{"learn":[1.673837925],"iteration":534,"passed_time":10.96742229,"remaining_time":8.179442047},
{"learn":[1.673812042],"iteration":535,"passed_time":10.98555978,"remaining_time":8.157188047},
{"learn":[1.673276045],"iteration":536,"passed_time":11.0058167,"remaining_time":8.13651626},
{"learn":[1.672884258],"iteration":537,"passed_time":11.0252211,"remaining_time":8.115218505},
{"learn":[1.672517953],"iteration":538,"passed_time":11.04395658,"remaining_time":8.093437565},
{"learn":[1.672176173],"iteration":539,"passed_time":11.06263729,"remaining_time":8.07162795},
{"learn":[1.671835622],"iteration":540,"passed_time":11.08285598,"remaining_time":8.050947133},
{"learn":[1.671258066],"iteration":541,"passed_time":11.1028076,"remaining_time":8.030074869},
{"learn":[1.670961968],"iteration":542,"passed_time":11.12604777,"remaining_time":8.011573996},
{"learn":[1.670622271],"iteration":543,"passed_time":11.14475132,"remaining_time":7.989803334},
{"learn":[1.670170128],"iteration":544,"passed_time":11.16539662,"remaining_time":7.969429884},
{"learn":[1.670049374],"iteration":545,"passed_time":11.18330595,"remaining_time":7.947111189},
{"learn":[1.669659969],"iteration":546,"passed_time":11.20494166,"remaining_time":7.927445016},
{"learn":[1.669413213],"iteration":547,"passed_time":11.22522869,"remaining_time":7.906821669},
{"learn":[1.669098473],"iteration":548,"passed_time":11.24860893,"remaining_time":7.888368742},
{"learn":[1.668901578],"iteration":549,"passed_time":11.2687516,"remaining_time":7.867637484},
{"learn":[1.668650601],"iteration":550,"passed_time":11.29003983,"remaining_time":7.847704638},
{"learn":[1.668573418],"iteration":551,"passed_time":11.30997985,"remaining_time":7.826833881},
{"learn":[1.668045799],"iteration":552,"passed_time":11.3306948,"remaining_time":7.806500395},
{"learn":[1.667760941],"iteration":553,"passed_time":11.34849436,"remaining_time":7.784165807},
{"learn":[1.667417167],"iteration":554,"passed_time":11.37026738,"remaining_time":7.764560965},
{"learn":[1.667201029],"iteration":555,"passed_time":11.38684426,"remaining_time":7.741415699},
{"learn":[1.666636689],"iteration":556,"passed_time":11.40685971,"remaining_time":7.720621381},
{"learn":[1.666276219],"iteration":557,"passed_time":11.42601028,"remaining_time":7.699247073},
{"learn":[1.665845323],"iteration":558,"passed_time":11.44407627,"remaining_time":7.677153132},
{"learn":[1.665462199],"iteration":559,"passed_time":11.46402244,"remaining_time":7.656329275},
{"learn":[1.664982566],"iteration":560,"passed_time":11.484317,"remaining_time":7.635740179},
{"learn":[1.664797934],"iteration":561,"passed_time":11.50287058,"remaining_time":7.613999745},
{"learn":[1.66437443],"iteration":562,"passed_time":11.52118259,"remaining_time":7.592111443},
{"learn":[1.663849224],"iteration":563,"passed_time":11.53991641,"remaining_time":7.57051254},
{"learn":[1.663544533],"iteration":564,"passed_time":11.55832623,"remaining_time":7.548712173},
{"learn":[1.663321411],"iteration":565,"passed_time":11.57668034,"remaining_time":7.526887574},
{"learn":[1.662800187],"iteration":566,"passed_time":11.59712722,"remaining_time":7.506429788},
{"learn":[1.66244009],"iteration":567,"passed_time":11.61855927,"remaining_time":7.486606856},
{"learn":[1.66185748],"iteration":568,"passed_time":11.64110329,"remaining_time":7.467491565},
{"learn":[1.661467363],"iteration":569,"passed_time":11.6604261,"remaining_time":7.446307195},
{"learn":[1.660975217],"iteration":570,"passed_time":11.68111921,"remaining_time":7.426000476},
{"learn":[1.660711066],"iteration":571,"passed_time":11.69929648,"remaining_time":7.404100218},
{"learn":[1.660494703],"iteration":572,"passed_time":11.71609961,"remaining_time":7.381347223},
{"learn":[1.660184471],"iteration":573,"passed_time":11.73731567,"remaining_time":7.361382648},
{"learn":[1.659652641],"iteration":574,"passed_time":11.76034821,"remaining_time":7.342547836},
{"learn":[1.659436022],"iteration":575,"passed_time":11.78234668,"remaining_time":7.323055752},
{"learn":[1.659093876],"iteration":576,"passed_time":11.80526421,"remaining_time":7.304123609},
{"learn":[1.659040543],"iteration":577,"passed_time":11.82335441,"remaining_time":7.282204447},
{"learn":[1.658653917],"iteration":578,"passed_time":11.84296636,"remaining_time":7.261231533},
{"learn":[1.658378035],"iteration":579,"passed_time":11.86218778,"remaining_time":7.240024955},
{"learn":[1.658343987],"iteration":580,"passed_time":11.87809193,"remaining_time":7.21680973},
{"learn":[1.658041444],"iteration":581,"passed_time":11.89913552,"remaining_time":7.196728013},
{"learn":[1.657864177],"iteration":582,"passed_time":11.91739161,"remaining_time":7.174964761},
{"learn":[1.657726211],"iteration":583,"passed_time":11.93773762,"remaining_time":7.154466037},
{"learn":[1.657195814],"iteration":584,"passed_time":11.95934349,"remaining_time":7.134719449},
{"learn":[1.656962842],"iteration":585,"passed_time":11.97791086,"remaining_time":7.113162078},
{"learn":[1.656809115],"iteration":586,"passed_time":11.99748598,"remaining_time":7.092210622},
{"learn":[1.656438808],"iteration":587,"passed_time":12.01528636,"remaining_time":7.070219524},
{"learn":[1.656233412],"iteration":588,"passed_time":12.03419807,"remaining_time":7.048893606},
{"learn":[1.656043027],"iteration":589,"passed_time":12.05287595,"remaining_time":7.027439535},
{"learn":[1.655966778],"iteration":590,"passed_time":12.06951413,"remaining_time":7.004811079},
{"learn":[1.655670085],"iteration":591,"passed_time":12.08793551,"remaining_time":6.983233011},
{"learn":[1.655253597],"iteration":592,"passed_time":12.10592701,"remaining_time":6.961418401},
{"learn":[1.654810886],"iteration":593,"passed_time":12.12748386,"remaining_time":6.941657427},
{"learn":[1.654454038],"iteration":594,"passed_time":12.14863563,"remaining_time":6.921659626},
{"learn":[1.654323566],"iteration":595,"passed_time":12.16823237,"remaining_time":6.900776078},
{"learn":[1.65396027],"iteration":596,"passed_time":12.18748696,"remaining_time":6.879703695},
{"learn":[1.653734416],"iteration":597,"passed_time":12.20835207,"remaining_time":6.859542302},
{"learn":[1.653287672],"iteration":598,"passed_time":12.23187088,"remaining_time":6.840862678},
{"learn":[1.652975739],"iteration":599,"passed_time":12.25254453,"remaining_time":6.82058312},
{"learn":[1.652795106],"iteration":600,"passed_time":12.27093248,"remaining_time":6.799035799},
{"learn":[1.652399421],"iteration":601,"passed_time":12.29143015,"remaining_time":6.778662476},
{"learn":[1.652284977],"iteration":602,"passed_time":12.30795958,"remaining_time":6.756110482},
{"learn":[1.652095463],"iteration":603,"passed_time":12.32959528,"remaining_time":6.736368284},
{"learn":[1.651887654],"iteration":604,"passed_time":12.34863817,"remaining_time":6.715209847},
{"learn":[1.651737373],"iteration":605,"passed_time":12.37121488,"remaining_time":6.695971088},
{"learn":[1.651589004],"iteration":606,"passed_time":12.39283308,"remaining_time":6.676204969},
{"learn":[1.651324064],"iteration":607,"passed_time":12.41834629,"remaining_time":6.658521203},
{"learn":[1.650972572],"iteration":608,"passed_time":12.43758228,"remaining_time":6.637461807},
{"learn":[1.65089772],"iteration":609,"passed_time":12.45550121,"remaining_time":6.61570884},
{"learn":[1.650857704],"iteration":610,"passed_time":12.47151295,"remaining_time":6.592960202},
{"learn":[1.65055713],"iteration":611,"passed_time":12.49197401,"remaining_time":6.572574558},
{"learn":[1.650289898],"iteration":612,"passed_time":12.512889,"remaining_time":6.552426377},
{"learn":[1.649852712],"iteration":613,"passed_time":12.53289595,"remaining_time":6.53180245},
{"learn":[1.649431559],"iteration":614,"passed_time":12.55203793,"remaining_time":6.510731867},
{"learn":[1.649109056],"iteration":615,"passed_time":12.57320661,"remaining_time":6.490713801},
{"learn":[1.648970854],"iteration":616,"passed_time":12.59074552,"remaining_time":6.468827113},
{"learn":[1.648658314],"iteration":617,"passed_time":12.60736498,"remaining_time":6.446484361},
{"learn":[1.648580773],"iteration":618,"passed_time":12.62933136,"remaining_time":6.426881064},
{"learn":[1.648186092],"iteration":619,"passed_time":12.64889516,"remaining_time":6.406053358},
{"learn":[1.647844226],"iteration":620,"passed_time":12.66780648,"remaining_time":6.384900852},
{"learn":[1.64762228],"iteration":621,"passed_time":12.69091669,"remaining_time":6.365861746},
{"learn":[1.647433806],"iteration":622,"passed_time":12.7119923,"remaining_time":6.345793907},
{"learn":[1.647053465],"iteration":623,"passed_time":12.73149317,"remaining_time":6.324940517},
{"learn":[1.646610341],"iteration":624,"passed_time":12.75279762,"remaining_time":6.304983142},
{"learn":[1.646551252],"iteration":625,"passed_time":12.76939333,"remaining_time":6.282704706},
{"learn":[1.646471479],"iteration":626,"passed_time":12.79097138,"remaining_time":6.262883912},
{"learn":[1.646118461],"iteration":627,"passed_time":12.81695454,"remaining_time":6.245203966},
{"learn":[1.645625235],"iteration":628,"passed_time":12.84472799,"remaining_time":6.228365721},
{"learn":[1.645323859],"iteration":629,"passed_time":12.86830521,"remaining_time":6.209467911},
{"learn":[1.645033115],"iteration":630,"passed_time":12.89127655,"remaining_time":6.190264332},
{"learn":[1.64456742],"iteration":631,"passed_time":12.91572636,"remaining_time":6.171755318},
{"learn":[1.64423836],"iteration":632,"passed_time":12.93500159,"remaining_time":6.150766949},
{"learn":[1.643964529],"iteration":633,"passed_time":12.9546696,"remaining_time":6.129969843},
{"learn":[1.643706711],"iteration":634,"passed_time":12.97168829,"remaining_time":6.107928817},
{"learn":[1.64326643],"iteration":635,"passed_time":12.98904021,"remaining_time":6.086059723},
{"learn":[1.643226317],"iteration":636,"passed_time":13.00310387,"remaining_time":6.062671662},
{"learn":[1.643158963],"iteration":637,"passed_time":13.02572493,"remaining_time":6.043283039},
{"learn":[1.642818427],"iteration":638,"passed_time":13.04595236,"remaining_time":6.022779261},
{"learn":[1.642370791],"iteration":639,"passed_time":13.06635902,"remaining_time":6.002358676},
{"learn":[1.641929357],"iteration":640,"passed_time":13.08518682,"remaining_time":5.981216442},
{"learn":[1.641916479],"iteration":641,"passed_time":13.09628985,"remaining_time":5.956567968},
{"learn":[1.641675272],"iteration":642,"passed_time":13.1126087,"remaining_time":5.934322132},
{"learn":[1.64165715],"iteration":643,"passed_time":13.12541543,"remaining_time":5.910513157},
{"learn":[1.641485167],"iteration":644,"passed_time":13.14404565,"remaining_time":5.889347588},
{"learn":[1.641147351],"iteration":645,"passed_time":13.16109877,"remaining_time":5.867486759},
{"learn":[1.641081815],"iteration":646,"passed_time":13.1768462,"remaining_time":5.845061608},
{"learn":[1.640728115],"iteration":647,"passed_time":13.19451576,"remaining_time":5.823505411},
{"learn":[1.640553549],"iteration":648,"passed_time":13.21264076,"remaining_time":5.802161198},
{"learn":[1.640456323],"iteration":649,"passed_time":13.22977533,"remaining_time":5.780394143},
{"learn":[1.640401938],"iteration":650,"passed_time":13.24929988,"remaining_time":5.759680284},
{"learn":[1.640279012],"iteration":651,"passed_time":13.26628764,"remaining_time":5.737872876},
{"learn":[1.639916651],"iteration":652,"passed_time":13.28599689,"remaining_time":5.717251342},
{"learn":[1.639666944],"iteration":653,"passed_time":13.30426442,"remaining_time":5.69601535},
{"learn":[1.639367545],"iteration":654,"passed_time":13.32651911,"remaining_time":5.676486766},
{"learn":[1.638939241],"iteration":655,"passed_time":13.34635888,"remaining_time":5.655926476},
{"learn":[1.638653748],"iteration":656,"passed_time":13.3610165,"remaining_time":5.633183515},
{"learn":[1.638256389],"iteration":657,"passed_time":13.38010963,"remaining_time":5.61232562},
{"learn":[1.637909694],"iteration":658,"passed_time":13.39655562,"remaining_time":5.590368431},
{"learn":[1.637611446],"iteration":659,"passed_time":13.41497293,"remaining_time":5.569246338},
{"learn":[1.637155867],"iteration":660,"passed_time":13.44031956,"remaining_time":5.550994312},
{"learn":[1.636801219],"iteration":661,"passed_time":13.46405713,"remaining_time":5.532059727},
{"learn":[1.636788382],"iteration":662,"passed_time":13.48094883,"remaining_time":5.510312419},
{"learn":[1.636523642],"iteration":663,"passed_time":13.501129,"remaining_time":5.489916915},
{"learn":[1.636166942],"iteration":664,"passed_time":13.51872977,"remaining_time":5.468478661},
{"learn":[1.63603549],"iteration":665,"passed_time":13.53802676,"remaining_time":5.447734493},
{"learn":[1.635767265],"iteration":666,"passed_time":13.55268132,"remaining_time":5.425136299},
{"learn":[1.635492902],"iteration":667,"passed_time":13.57154797,"remaining_time":5.404239161},
{"learn":[1.635449806],"iteration":668,"passed_time":13.58486317,"remaining_time":5.381149087},
{"learn":[1.635331912],"iteration":669,"passed_time":13.60309447,"remaining_time":5.360025283},
{"learn":[1.634928301],"iteration":670,"passed_time":13.62265907,"remaining_time":5.339432691},
{"learn":[1.63455542],"iteration":671,"passed_time":13.64063146,"remaining_time":5.318222386},
{"learn":[1.634521229],"iteration":672,"passed_time":13.65579752,"remaining_time":5.295933362},
{"learn":[1.634463439],"iteration":673,"passed_time":13.67156185,"remaining_time":5.273896263},
{"learn":[1.634156564],"iteration":674,"passed_time":13.68969105,"remaining_time":5.252785159},
{"learn":[1.633825811],"iteration":675,"passed_time":13.70399799,"remaining_time":5.230224086},
{"learn":[1.633716575],"iteration":676,"passed_time":13.71869879,"remaining_time":5.207836913},
{"learn":[1.633652957],"iteration":677,"passed_time":13.73615374,"remaining_time":5.186512328},
{"learn":[1.63334849],"iteration":678,"passed_time":13.75642183,"remaining_time":5.166255621},
{"learn":[1.633198718],"iteration":679,"passed_time":13.77500476,"remaining_time":5.145369427},
{"learn":[1.632941632],"iteration":680,"passed_time":13.79532423,"remaining_time":5.125135141},
{"learn":[1.632438474],"iteration":681,"passed_time":13.81489261,"remaining_time":5.104623075},
{"learn":[1.632330828],"iteration":682,"passed_time":13.82995298,"remaining_time":5.082457097},
{"learn":[1.632190748],"iteration":683,"passed_time":13.84563714,"remaining_time":5.060539891},
{"learn":[1.632028897],"iteration":684,"passed_time":13.86093968,"remaining_time":5.03850216},
{"learn":[1.63188703],"iteration":685,"passed_time":13.87796711,"remaining_time":5.017107645},
{"learn":[1.631432449],"iteration":686,"passed_time":13.8965918,"remaining_time":4.99630011},
{"learn":[1.631377827],"iteration":687,"passed_time":13.9135233,"remaining_time":4.974893504},
{"learn":[1.630974212],"iteration":688,"passed_time":13.93572905,"remaining_time":4.95537535},
{"learn":[1.630688231],"iteration":689,"passed_time":13.95638607,"remaining_time":4.93530174},
{"learn":[1.63029782],"iteration":690,"passed_time":13.98134235,"remaining_time":4.916738336},
{"learn":[1.629919495],"iteration":691,"passed_time":14.00403009,"remaining_time":4.897363125},
{"learn":[1.629717924],"iteration":692,"passed_time":14.02253337,"remaining_time":4.876523147},
{"learn":[1.629397927],"iteration":693,"passed_time":14.03998982,"remaining_time":4.855327893},
{"learn":[1.629095944],"iteration":694,"passed_time":14.0548728,"remaining_time":4.833258415},
{"learn":[1.628781318],"iteration":695,"passed_time":14.07348019,"remaining_time":4.812483169},
{"learn":[1.628602819],"iteration":696,"passed_time":14.09175177,"remaining_time":4.791599955},
{"learn":[1.628217575],"iteration":697,"passed_time":14.1118439,"remaining_time":4.771339771},
{"learn":[1.6280589],"iteration":698,"passed_time":14.12976233,"remaining_time":4.750349283},
{"learn":[1.627596593],"iteration":699,"passed_time":14.14730146,"remaining_time":4.729240775},
{"learn":[1.62732558],"iteration":700,"passed_time":14.17042345,"remaining_time":4.709998095},
{"learn":[1.627158696],"iteration":701,"passed_time":14.18734511,"remaining_time":4.688695251},
{"learn":[1.626952197],"iteration":702,"passed_time":14.2038446,"remaining_time":4.667266147},
{"learn":[1.626435568],"iteration":703,"passed_time":14.22392185,"remaining_time":4.647019923},
{"learn":[1.62630354],"iteration":704,"passed_time":14.2412778,"remaining_time":4.625890235},
{"learn":[1.626082055],"iteration":705,"passed_time":14.25797967,"remaining_time":4.604560007},
{"learn":[1.625834113],"iteration":706,"passed_time":14.27803382,"remaining_time":4.584319203},
{"learn":[1.625592829],"iteration":707,"passed_time":14.30270521,"remaining_time":4.565552793},
{"learn":[1.625489924],"iteration":708,"passed_time":14.31976889,"remaining_time":4.54435543},
{"learn":[1.625076113],"iteration":709,"passed_time":14.33834074,"remaining_time":4.52364553},
{"learn":[1.624700323],"iteration":710,"passed_time":14.35688556,"remaining_time":4.502933165},
{"learn":[1.624211001],"iteration":711,"passed_time":14.37701202,"remaining_time":4.482720041},
{"learn":[1.623758666],"iteration":712,"passed_time":14.39705386,"remaining_time":4.46248093},
{"learn":[1.623634895],"iteration":713,"passed_time":14.4140492,"remaining_time":4.441303675},
{"learn":[1.623499981],"iteration":714,"passed_time":14.42660835,"remaining_time":4.418779342},
{"learn":[1.623189006],"iteration":715,"passed_time":14.45321036,"remaining_time":4.400558462},
{"learn":[1.622981144],"iteration":716,"passed_time":14.470737,"remaining_time":4.379567543},
{"learn":[1.622943507],"iteration":717,"passed_time":14.48758143,"remaining_time":4.358381042},
{"learn":[1.622919662],"iteration":718,"passed_time":14.50689235,"remaining_time":4.337944166},
{"learn":[1.622647503],"iteration":719,"passed_time":14.52696361,"remaining_time":4.317736407},
{"learn":[1.622448956],"iteration":720,"passed_time":14.54868679,"remaining_time":4.298017041},
{"learn":[1.621900788],"iteration":721,"passed_time":14.57263515,"remaining_time":4.2789455},
{"learn":[1.62161481],"iteration":722,"passed_time":14.59204126,"remaining_time":4.258534863},
{"learn":[1.621579458],"iteration":723,"passed_time":14.60674189,"remaining_time":4.236762151},
{"learn":[1.621432992],"iteration":724,"passed_time":14.62617954,"remaining_time":4.216374515},
{"learn":[1.621200823],"iteration":725,"passed_time":14.64728599,"remaining_time":4.19646761},
{"learn":[1.62096296],"iteration":726,"passed_time":14.67232592,"remaining_time":4.177677393},
{"learn":[1.620673236],"iteration":727,"passed_time":14.6986489,"remaining_time":4.159233068},
{"learn":[1.620639943],"iteration":728,"passed_time":14.72134271,"remaining_time":4.139746578},
{"learn":[1.620487167],"iteration":729,"passed_time":14.74518136,"remaining_time":4.120571231},
{"learn":[1.62018677],"iteration":730,"passed_time":14.77241308,"remaining_time":4.102325383},
{"learn":[1.61987798],"iteration":731,"passed_time":14.79870391,"remaining_time":4.083795341},
{"learn":[1.619531724],"iteration":732,"passed_time":14.8229146,"remaining_time":4.064673718},
{"learn":[1.619282815],"iteration":733,"passed_time":14.85672263,"remaining_time":4.048153305},
{"learn":[1.619072838],"iteration":734,"passed_time":14.88149387,"remaining_time":4.029139157},
{"learn":[1.619010713],"iteration":735,"passed_time":14.90098612,"remaining_time":4.008689202},
{"learn":[1.61887227],"iteration":736,"passed_time":14.93262713,"remaining_time":3.991489207},
{"learn":[1.618734632],"iteration":737,"passed_time":14.96454356,"remaining_time":3.974323221},
{"learn":[1.618690959],"iteration":738,"passed_time":14.98714151,"remaining_time":3.95465845},
{"learn":[1.618574025],"iteration":739,"passed_time":15.01445574,"remaining_time":3.936222182},
{"learn":[1.618406289],"iteration":740,"passed_time":15.0409262,"remaining_time":3.917542181},
{"learn":[1.618036929],"iteration":741,"passed_time":15.06898947,"remaining_time":3.899253341},
{"learn":[1.617582307],"iteration":742,"passed_time":15.09222323,"remaining_time":3.879696684},
{"learn":[1.617403105],"iteration":743,"passed_time":15.11200693,"remaining_time":3.859249083},
{"learn":[1.617365055],"iteration":744,"passed_time":15.13045432,"remaining_time":3.838464251},
{"learn":[1.617153295],"iteration":745,"passed_time":15.15130268,"remaining_time":3.818290755},
{"learn":[1.616845849],"iteration":746,"passed_time":15.17343217,"remaining_time":3.798436166},
{"learn":[1.616472274],"iteration":747,"passed_time":15.19684222,"remaining_time":3.778893922},
{"learn":[1.616000506],"iteration":748,"passed_time":15.22094102,"remaining_time":3.759511466},
{"learn":[1.615620174],"iteration":749,"passed_time":15.24755417,"remaining_time":3.740733289},
{"learn":[1.615576981],"iteration":750,"passed_time":15.2646871,"remaining_time":3.719624154},
{"learn":[1.615060798],"iteration":751,"passed_time":15.28529998,"remaining_time":3.699367814},
{"learn":[1.614559906],"iteration":752,"passed_time":15.30546902,"remaining_time":3.679003842},
{"learn":[1.614516902],"iteration":753,"passed_time":15.32368851,"remaining_time":3.658174976},
{"learn":[1.614112593],"iteration":754,"passed_time":15.34602847,"remaining_time":3.638329929},
{"learn":[1.614080782],"iteration":755,"passed_time":15.36028635,"remaining_time":3.616575359},
{"learn":[1.613705919],"iteration":756,"passed_time":15.38088787,"remaining_time":3.596323849},
{"learn":[1.613394723],"iteration":757,"passed_time":15.40324525,"remaining_time":3.576479107},
{"learn":[1.613228433],"iteration":758,"passed_time":15.42261652,"remaining_time":3.55593925},
{"learn":[1.612989661],"iteration":759,"passed_time":15.43923857,"remaining_time":3.534773041},
{"learn":[1.612829813],"iteration":760,"passed_time":15.45612178,"remaining_time":3.513678144},
{"learn":[1.612536055],"iteration":761,"passed_time":15.47881486,"remaining_time":3.493905715},
{"learn":[1.612091236],"iteration":762,"passed_time":15.50061885,"remaining_time":3.473926375},
{"learn":[1.612049309],"iteration":763,"passed_time":15.51983081,"remaining_time":3.453365494},
{"learn":[1.611941413],"iteration":764,"passed_time":15.5359306,"remaining_time":3.432120617},
{"learn":[1.611824887],"iteration":765,"passed_time":15.5536507,"remaining_time":3.411244541},
{"learn":[1.611611979],"iteration":766,"passed_time":15.57062691,"remaining_time":3.390214725},
{"learn":[1.6115878],"iteration":767,"passed_time":15.5865272,"remaining_time":3.36896291},
{"learn":[1.611234415],"iteration":768,"passed_time":15.60945779,"remaining_time":3.349233466},
{"learn":[1.610937875],"iteration":769,"passed_time":15.63094571,"remaining_time":3.329188438},
{"learn":[1.610896289],"iteration":770,"passed_time":15.65059749,"remaining_time":3.308751479},
{"learn":[1.610664213],"iteration":771,"passed_time":15.67216219,"remaining_time":3.288717973},
{"learn":[1.610317682],"iteration":772,"passed_time":15.69419363,"remaining_time":3.268777715},
{"learn":[1.609952597],"iteration":773,"passed_time":15.71642902,"remaining_time":3.248874217},
{"learn":[1.609783981],"iteration":774,"passed_time":15.73176814,"remaining_time":3.227549851},
{"learn":[1.609105442],"iteration":775,"passed_time":15.75117842,"remaining_time":3.207069834},
{"learn":[1.608740797],"iteration":776,"passed_time":15.77328911,"remaining_time":3.187138211},
{"learn":[1.608522956],"iteration":777,"passed_time":15.78549444,"remaining_time":3.165214823},
{"learn":[1.608413126],"iteration":778,"passed_time":15.80323011,"remaining_time":3.144416773},
{"learn":[1.608373202],"iteration":779,"passed_time":15.8170856,"remaining_time":3.12286049},
{"learn":[1.608020618],"iteration":780,"passed_time":15.83668094,"remaining_time":3.102448379},
{"learn":[1.60796872],"iteration":781,"passed_time":15.85051179,"remaining_time":3.080917893},
{"learn":[1.607948879],"iteration":782,"passed_time":15.86584743,"remaining_time":3.05969727},
{"learn":[1.607792185],"iteration":783,"passed_time":15.88086213,"remaining_time":3.038430254},
{"learn":[1.60776584],"iteration":784,"passed_time":15.89650101,"remaining_time":3.017297643},
{"learn":[1.607638936],"iteration":785,"passed_time":15.91128439,"remaining_time":2.996017925},
{"learn":[1.607331548],"iteration":786,"passed_time":15.9297537,"remaining_time":2.975443194},
{"learn":[1.606911998],"iteration":787,"passed_time":15.94734335,"remaining_time":2.954710824},
{"learn":[1.606629852],"iteration":788,"passed_time":15.96806185,"remaining_time":2.93456143},
{"learn":[1.606335338],"iteration":789,"passed_time":15.9863737,"remaining_time":2.913971915},
{"learn":[1.606053843],"iteration":790,"passed_time":16.00831608,"remaining_time":2.8940445},
{"learn":[1.605924549],"iteration":791,"passed_time":16.02333836,"remaining_time":2.872871271},
{"learn":[1.605907052],"iteration":792,"passed_time":16.0420072,"remaining_time":2.852361936},
{"learn":[1.605678368],"iteration":793,"passed_time":16.06121038,"remaining_time":2.831951452},
{"learn":[1.605556051],"iteration":794,"passed_time":16.07813318,"remaining_time":2.811145298},
{"learn":[1.605268579],"iteration":795,"passed_time":16.09488486,"remaining_time":2.790319234},
{"learn":[1.604861129],"iteration":796,"passed_time":16.11751407,"remaining_time":2.770513711},
{"learn":[1.604525853],"iteration":797,"passed_time":16.13957157,"remaining_time":2.750603677},
{"learn":[1.604400402],"iteration":798,"passed_time":16.16100556,"remaining_time":2.730582917},
{"learn":[1.604368329],"iteration":799,"passed_time":16.17843918,"remaining_time":2.709888563},
{"learn":[1.604147123],"iteration":800,"passed_time":16.19604689,"remaining_time":2.689231257},
{"learn":[1.603897109],"iteration":801,"passed_time":16.21423943,"remaining_time":2.668677811},
{"learn":[1.603558348],"iteration":802,"passed_time":16.23966523,"remaining_time":2.649310268},
{"learn":[1.603474089],"iteration":803,"passed_time":16.25810195,"remaining_time":2.628797579},
{"learn":[1.603348946],"iteration":804,"passed_time":16.27649983,"remaining_time":2.608283824},
{"learn":[1.603152497],"iteration":805,"passed_time":16.29613914,"remaining_time":2.587972469},
{"learn":[1.60266574],"iteration":806,"passed_time":16.31589022,"remaining_time":2.567680369},
{"learn":[1.602356873],"iteration":807,"passed_time":16.33566355,"remaining_time":2.547393078},
{"learn":[1.602259263],"iteration":808,"passed_time":16.35320537,"remaining_time":2.526762264},
{"learn":[1.601919335],"iteration":809,"passed_time":16.37413332,"remaining_time":2.506657446},
{"learn":[1.601535421],"iteration":810,"passed_time":16.3943211,"remaining_time":2.486438343},
{"learn":[1.601483702],"iteration":811,"passed_time":16.41295367,"remaining_time":2.465985649},
{"learn":[1.601187629],"iteration":812,"passed_time":16.43406789,"remaining_time":2.445906783},
{"learn":[1.601088589],"iteration":813,"passed_time":16.44902604,"remaining_time":2.424917844},
{"learn":[1.600989012],"iteration":814,"passed_time":16.46348291,"remaining_time":2.403870511},
{"learn":[1.600856857],"iteration":815,"passed_time":16.47950506,"remaining_time":2.383065682},
{"learn":[1.600781402],"iteration":816,"passed_time":16.49191102,"remaining_time":2.3617547},
{"learn":[1.600575626],"iteration":817,"passed_time":16.50785068,"remaining_time":2.340966599},
{"learn":[1.600232982],"iteration":818,"passed_time":16.52634282,"remaining_time":2.320548748},
{"learn":[1.599872261],"iteration":819,"passed_time":16.54768342,"remaining_time":2.300531597},
{"learn":[1.599555863],"iteration":820,"passed_time":16.56465883,"remaining_time":2.279910412},
{"learn":[1.59927797],"iteration":821,"passed_time":16.58098799,"remaining_time":2.259210043},
{"learn":[1.599242474],"iteration":822,"passed_time":16.59746508,"remaining_time":2.238540248},
{"learn":[1.598983511],"iteration":823,"passed_time":16.61650517,"remaining_time":2.218222778},
{"learn":[1.598861998],"iteration":824,"passed_time":16.63434403,"remaining_time":2.197749697},
{"learn":[1.598629103],"iteration":825,"passed_time":16.65557247,"remaining_time":2.177726182},
{"learn":[1.59825624],"iteration":826,"passed_time":16.67633413,"remaining_time":2.157639362},
{"learn":[1.598015311],"iteration":827,"passed_time":16.69863306,"remaining_time":2.137747711},
{"learn":[1.597603996],"iteration":828,"passed_time":16.72070838,"remaining_time":2.117821929},
{"learn":[1.597394765],"iteration":829,"passed_time":16.73735931,"remaining_time":2.097211287},
{"learn":[1.596982965],"iteration":830,"passed_time":16.76149789,"remaining_time":2.077538246},
{"learn":[1.596710547],"iteration":831,"passed_time":16.78070236,"remaining_time":2.057249568},
{"learn":[1.596582068],"iteration":832,"passed_time":16.80052931,"remaining_time":2.037038967},
{"learn":[1.596526193],"iteration":833,"passed_time":16.82139696,"remaining_time":2.016954072},
{"learn":[1.595862302],"iteration":834,"passed_time":16.8430529,"remaining_time":1.996960763},
{"learn":[1.595640104],"iteration":835,"passed_time":16.86370929,"remaining_time":1.976846304},
{"learn":[1.595366832],"iteration":836,"passed_time":16.88154023,"remaining_time":1.956403109},
{"learn":[1.595125167],"iteration":837,"passed_time":16.89987412,"remaining_time":1.936023765},
{"learn":[1.594980635],"iteration":838,"passed_time":16.91486743,"remaining_time":1.915271044},
{"learn":[1.594661985],"iteration":839,"passed_time":16.93387768,"remaining_time":1.89498155},
{"learn":[1.594293667],"iteration":840,"passed_time":16.95331632,"remaining_time":1.87474247},
{"learn":[1.593903324],"iteration":841,"passed_time":16.97336222,"remaining_time":1.854571644},
{"learn":[1.593319213],"iteration":842,"passed_time":16.99356486,"remaining_time":1.834418034},
{"learn":[1.593096402],"iteration":843,"passed_time":17.01194006,"remaining_time":1.814069438},
{"learn":[1.592742017],"iteration":844,"passed_time":17.02993793,"remaining_time":1.79368577},
{"learn":[1.592412986],"iteration":845,"passed_time":17.05216645,"remaining_time":1.773747811},
{"learn":[1.592205221],"iteration":846,"passed_time":17.06962641,"remaining_time":1.753314637},
{"learn":[1.592119238],"iteration":847,"passed_time":17.08400847,"remaining_time":1.73257633},
{"learn":[1.592059612],"iteration":848,"passed_time":17.10071472,"remaining_time":1.712085691},
{"learn":[1.591767663],"iteration":849,"passed_time":17.12320968,"remaining_time":1.692176015},
{"learn":[1.591703185],"iteration":850,"passed_time":17.14073955,"remaining_time":1.671776008},
{"learn":[1.591553634],"iteration":851,"passed_time":17.15781966,"remaining_time":1.65133945},
{"learn":[1.591274548],"iteration":852,"passed_time":17.17934943,"remaining_time":1.631333299},
{"learn":[1.591034053],"iteration":853,"passed_time":17.19973543,"remaining_time":1.611216433},
{"learn":[1.590812109],"iteration":854,"passed_time":17.21993059,"remaining_time":1.591081306},
{"learn":[1.590643264],"iteration":855,"passed_time":17.2406388,"remaining_time":1.570992787},
{"learn":[1.59048965],"iteration":856,"passed_time":17.26669422,"remaining_time":1.551383261},
{"learn":[1.590408932],"iteration":857,"passed_time":17.28633817,"remaining_time":1.531190794},
{"learn":[1.590058031],"iteration":858,"passed_time":17.30676262,"remaining_time":1.511067749},
{"learn":[1.589594733],"iteration":859,"passed_time":17.33018761,"remaining_time":1.49120219},
{"learn":[1.589568912],"iteration":860,"passed_time":17.35216787,"remaining_time":1.47120587},
{"learn":[1.58940923],"iteration":861,"passed_time":17.37320603,"remaining_time":1.451126258},
{"learn":[1.589197606],"iteration":862,"passed_time":17.39189451,"remaining_time":1.430851112},
{"learn":[1.588880647],"iteration":863,"passed_time":17.4166475,"remaining_time":1.411070978},
{"learn":[1.588704073],"iteration":864,"passed_time":17.43558243,"remaining_time":1.390815246},
{"learn":[1.588450364],"iteration":865,"passed_time":17.45474343,"remaining_time":1.370580316},
{"learn":[1.588023377],"iteration":866,"passed_time":17.47368361,"remaining_time":1.350330798},
{"learn":[1.587419028],"iteration":867,"passed_time":17.49546375,"remaining_time":1.330300239},
{"learn":[1.587038873],"iteration":868,"passed_time":17.51635595,"remaining_time":1.310199237},
{"learn":[1.586895001],"iteration":869,"passed_time":17.53146902,"remaining_time":1.289671284},
{"learn":[1.586594136],"iteration":870,"passed_time":17.54848078,"remaining_time":1.269293099},
{"learn":[1.586336812],"iteration":871,"passed_time":17.56476875,"remaining_time":1.248871172},
{"learn":[1.585976228],"iteration":872,"passed_time":17.58228688,"remaining_time":1.228544673},
{"learn":[1.585890586],"iteration":873,"passed_time":17.60053447,"remaining_time":1.208274678},
{"learn":[1.585542136],"iteration":874,"passed_time":17.61956925,"remaining_time":1.188062384},
{"learn":[1.585445306],"iteration":875,"passed_time":17.63736155,"remaining_time":1.167770514},
{"learn":[1.585187777],"iteration":876,"passed_time":17.65775278,"remaining_time":1.147653259},
{"learn":[1.585183749],"iteration":877,"passed_time":17.66986955,"remaining_time":1.127007625},
{"learn":[1.584891347],"iteration":878,"passed_time":17.68610655,"remaining_time":1.106639204},
{"learn":[1.584671061],"iteration":879,"passed_time":17.70252438,"remaining_time":1.086291269},
{"learn":[1.584454267],"iteration":880,"passed_time":17.71843035,"remaining_time":1.065921463},
{"learn":[1.583893909],"iteration":881,"passed_time":17.73988501,"remaining_time":1.045888912},
{"learn":[1.583545141],"iteration":882,"passed_time":17.76491402,"remaining_time":1.026059587},
{"learn":[1.583279733],"iteration":883,"passed_time":17.7886216,"remaining_time":1.006143756},
{"learn":[1.582859452],"iteration":884,"passed_time":17.81337674,"remaining_time":0.9862773563},
{"learn":[1.582799228],"iteration":885,"passed_time":17.83221016,"remaining_time":0.9660791056},
{"learn":[1.582513232],"iteration":886,"passed_time":17.85211568,"remaining_time":0.9459407405},
{"learn":[1.58224227],"iteration":887,"passed_time":17.8723702,"remaining_time":0.925820979},
{"learn":[1.58189013],"iteration":888,"passed_time":17.89027015,"remaining_time":0.9055817287},
{"learn":[1.581667991],"iteration":889,"passed_time":17.90792058,"remaining_time":0.8853353997},
{"learn":[1.581561182],"iteration":890,"passed_time":17.92178858,"remaining_time":0.8649123557},
{"learn":[1.581321949],"iteration":891,"passed_time":17.9404713,"remaining_time":0.8447307115},
{"learn":[1.581156713],"iteration":892,"passed_time":17.95671174,"remaining_time":0.8244402926},
{"learn":[1.580852953],"iteration":893,"passed_time":17.97058737,"remaining_time":0.804053126},
{"learn":[1.580517043],"iteration":894,"passed_time":17.98801387,"remaining_time":0.7838352414},
{"learn":[1.580429504],"iteration":895,"passed_time":18.01950608,"remaining_time":0.7642201239},
{"learn":[1.580234892],"iteration":896,"passed_time":18.05472952,"remaining_time":0.7447324329},
{"learn":[1.579758434],"iteration":897,"passed_time":18.08759839,"remaining_time":0.7251153031},
{"learn":[1.579721559],"iteration":898,"passed_time":18.108036,"remaining_time":0.7049847165},
{"learn":[1.57964009],"iteration":899,"passed_time":18.13545066,"remaining_time":0.6851170248},
{"learn":[1.579191543],"iteration":900,"passed_time":18.15448877,"remaining_time":0.6649257817},
{"learn":[1.578879843],"iteration":901,"passed_time":18.17447848,"remaining_time":0.6447708552},
{"learn":[1.578537013],"iteration":902,"passed_time":18.19777271,"remaining_time":0.6247297386},
{"learn":[1.578393838],"iteration":903,"passed_time":18.21706628,"remaining_time":0.6045486596},
{"learn":[1.578111775],"iteration":904,"passed_time":18.23633467,"remaining_time":0.5843687351},
{"learn":[1.577701373],"iteration":905,"passed_time":18.25679616,"remaining_time":0.5642276959},
{"learn":[1.577454057],"iteration":906,"passed_time":18.27841647,"remaining_time":0.5441204462},
{"learn":[1.57740784],"iteration":907,"passed_time":18.2915972,"remaining_time":0.5237682018},
{"learn":[1.576975116],"iteration":908,"passed_time":18.31458035,"remaining_time":0.5037013297},
{"learn":[1.576908976],"iteration":909,"passed_time":18.3347401,"remaining_time":0.4835535849},
{"learn":[1.576418698],"iteration":910,"passed_time":18.36079082,"remaining_time":0.4635545432},
{"learn":[1.576118472],"iteration":911,"passed_time":18.38002432,"remaining_time":0.4433777795},
{"learn":[1.575903629],"iteration":912,"passed_time":18.39952238,"remaining_time":0.4232091675},
{"learn":[1.575791957],"iteration":913,"passed_time":18.41816045,"remaining_time":0.4030232047},
{"learn":[1.575562604],"iteration":914,"passed_time":18.43818127,"remaining_time":0.3828693378},
{"learn":[1.575380716],"iteration":915,"passed_time":18.45791796,"remaining_time":0.3627101782},
{"learn":[1.575295133],"iteration":916,"passed_time":18.47276437,"remaining_time":0.3424612806},
{"learn":[1.575272993],"iteration":917,"passed_time":18.4834103,"remaining_time":0.3221509421},
{"learn":[1.57499621],"iteration":918,"passed_time":18.50184463,"remaining_time":0.3019887589},
{"learn":[1.57444727],"iteration":919,"passed_time":18.52141069,"remaining_time":0.2818475539},
{"learn":[1.574155015],"iteration":920,"passed_time":18.54116575,"remaining_time":0.2617102657},
{"learn":[1.573874085],"iteration":921,"passed_time":18.55924306,"remaining_time":0.2415519704},
{"learn":[1.573784319],"iteration":922,"passed_time":18.57681158,"remaining_time":0.2213921207},
{"learn":[1.573637683],"iteration":923,"passed_time":18.60471066,"remaining_time":0.2013496824},
{"learn":[1.573491883],"iteration":924,"passed_time":18.63202161,"remaining_time":0.1812845345},
{"learn":[1.573380676],"iteration":925,"passed_time":18.6488202,"remaining_time":0.1611129175},
{"learn":[1.573324622],"iteration":926,"passed_time":18.66505339,"remaining_time":0.1409443082},
{"learn":[1.573221431],"iteration":927,"passed_time":18.6814815,"remaining_time":0.1207854407},
{"learn":[1.573183585],"iteration":928,"passed_time":18.69818287,"remaining_time":0.1006360757},
{"learn":[1.572781392],"iteration":929,"passed_time":18.73099909,"remaining_time":0.08056343693},
{"learn":[1.572610963],"iteration":930,"passed_time":18.75863677,"remaining_time":0.06044673503},
{"learn":[1.572237692],"iteration":931,"passed_time":18.78988681,"remaining_time":0.04032164552},
{"learn":[1.571865728],"iteration":932,"passed_time":18.81422713,"remaining_time":0.02016530239},
{"learn":[1.571670246],"iteration":933,"passed_time":18.83863436,"remaining_time":0}
]}